cached_binance_data/__init__.py
cached_binance_data/cache.py
cached_binance_data/downloader.py
cached_binance_data-0.2.0.dist-info/METADATA
cached_binance_data-0.2.0.dist-info/WHEEL
cached_binance_data-0.2.0.dist-info/top_level.txt
cached_binance_data-0.2.0.dist-info/RECORD
