Metadata-Version: 2.2
Name: cached-binance-data
Version: 0.2.0
Summary: A lightweight Python module for downloading Binance futures market data with caching support
Home-page: https://github.com/kunthet/cached-binance-data
Author: Kunthet
Author-email: dev@kunthet.com
Classifier: Development Status :: 3 - Alpha
Classifier: Intended Audience :: Developers
Classifier: License :: OSI Approved :: MIT License
Classifier: Programming Language :: Python :: 3
Classifier: Programming Language :: Python :: 3.8
Classifier: Programming Language :: Python :: 3.9
Classifier: Programming Language :: Python :: 3.10
Requires-Python: >=3.8
Requires-Dist: requests>=2.26.0
Requires-Dist: python-binance>=1.0.16
Requires-Dist: python-dateutil>=2.8.2
Provides-Extra: test
Requires-Dist: pytest>=7.0.0; extra == "test"
Requires-Dist: pytest-cov>=2.0.0; extra == "test"
Dynamic: author
Dynamic: author-email
Dynamic: classifier
Dynamic: description
Dynamic: description-content-type
Dynamic: home-page
Dynamic: provides-extra
Dynamic: requires-dist
Dynamic: requires-python
Dynamic: summary
